ccconfig/__init__.py
ccconfig/simple_config.py
ccconfig-0.0.2.dist-info/METADATA
ccconfig-0.0.2.dist-info/WHEEL
ccconfig-0.0.2.dist-info/top_level.txt
ccconfig-0.0.2.dist-info/RECORD
